adre/__init__.py
adre/adr_template.md
adre/cli.py
adre/models.py
adre/utils.py
adre/server/__init__.py
adre/server/app.py
adre/server/controllers.py
adre/server/routes.py
adre/server/settings.py
adre/server/dist/favicon.ico
adre/server/dist/index.tpl
adre/server/dist/static/css/chunk-vendors.deae3966.css
adre/server/dist/static/img/logo.63a7d78d.svg
adre/server/dist/static/js/about.36bb091f.js
adre/server/dist/static/js/about.36bb091f.js.map
adre/server/dist/static/js/app.c18406e2.js
adre/server/dist/static/js/app.c18406e2.js.map
adre/server/dist/static/js/chunk-vendors.387baa92.js
adre/server/dist/static/js/chunk-vendors.387baa92.js.map
adre-0.0.1.dist-info/METADATA
adre-0.0.1.dist-info/WHEEL
adre-0.0.1.dist-info/entry_points.txt
adre-0.0.1.dist-info/top_level.txt
adre-0.0.1.dist-info/RECORD
