Metadata-Version: 2.1
Name: adre
Version: 0.0.1
Summary: ADR Extended
Home-page: UNKNOWN
License: UNKNOWN
Platform: UNKNOWN
Requires-Dist: click
Requires-Dist: bottle
